bsky_bridge/__init__.py
bsky_bridge/bsky_session.py
bsky_bridge/image_utilities.py
bsky_bridge/post_utilities.py
bsky_bridge-1.1.0.dist-info/licenses/LICENSE
bsky_bridge-1.1.0.dist-info/METADATA
bsky_bridge-1.1.0.dist-info/WHEEL
bsky_bridge-1.1.0.dist-info/top_level.txt
bsky_bridge-1.1.0.dist-info/RECORD
