Metadata-Version: 2.4
Name: bsky-bridge
Version: 1.1.0
Summary: A Python library for the BlueSky Social Network API
Author-email: Exal <hello@exal.sh>
License: MIT
Project-URL: Homepage, https://github.com/0xExal/bsky-bridge
Project-URL: Repository, https://github.com/0xExal/bsky-bridge
Project-URL: Issues, https://github.com/0xExal/bsky-bridge/issues
Keywords: bluesky,atproto,api,social-network,python
Classifier: Development Status :: 4 - Beta
Classifier: Programming Language :: Python :: 3
Classifier: Programming Language :: Python :: 3.9
Classifier: Programming Language :: Python :: 3.10
Classifier: Programming Language :: Python :: 3.11
Classifier: Programming Language :: Python :: 3.12
Classifier: Programming Language :: Python :: 3.13
Classifier: License :: OSI Approved :: MIT License
Classifier: Operating System :: OS Independent
Classifier: Intended Audience :: Developers
Classifier: Topic :: Internet
Classifier: Topic :: Software Development :: Libraries :: Python Modules
Requires-Python: >=3.9
License-File: LICENSE
Requires-Dist: requests
Requires-Dist: Pillow
Dynamic: license-file
